{
  "key": "plugin_content_manager_configuration_content_types::api::advertisement-template.advertisement-template",
  "value": {
    "settings": {
      "bulkable": true,
      "filterable": true,
      "searchable": true,
      "pageSize": 10,
      "mainField": "id",
      "defaultSortBy": "id",
      "defaultSortOrder": "ASC"
    },
    "metadatas": {
      "id": {
        "edit": {},
        "list": {
          "label": "id",
          "searchable": true,
          "sortable": true
        }
      },
      "name": {
        "edit": {
          "label": "name",
          "description": "",
          "placeholder": "",
          "visible": true,
          "editable": true
        },
        "list": {
          "label": "name",
          "searchable": true,
          "sortable": true
        }
      },
      "widthInColumns": {
        "edit": {
          "label": "widthInColumns",
          "description": "",
          "placeholder": "",
          "visible": true,
          "editable": true
        },
        "list": {
          "label": "widthInColumns",
          "searchable": true,
          "sortable": true
        }
      },
      "heightInRows": {
        "edit": {
          "label": "heightInRows",
          "description": "",
          "placeholder": "",
          "visible": true,
          "editable": true
        },
        "list": {
          "label": "heightInRows",
          "searchable": true,
          "sortable": true
        }
      },
      "advertisments": {
        "edit": {
          "label": "advertisments",
          "description": "",
          "placeholder": "",
          "visible": true,
          "editable": true,
          "mainField": "Header"
        },
        "list": {
          "label": "advertisments",
          "searchable": false,
          "sortable": false
        }
      },
      "createdAt": {
        "edit": {
          "label": "createdAt",
          "description": "",
          "placeholder": "",
          "visible": false,
          "editable": true
        },
        "list": {
          "label": "createdAt",
          "searchable": true,
          "sortable": true
        }
      },
      "updatedAt": {
        "edit": {
          "label": "updatedAt",
          "description": "",
          "placeholder": "",
          "visible": false,
          "editable": true
        },
        "list": {
          "label": "updatedAt",
          "searchable": true,
          "sortable": true
        }
      },
      "createdBy": {
        "edit": {
          "label": "createdBy",
          "description": "",
          "placeholder": "",
          "visible": false,
          "editable": true,
          "mainField": "firstname"
        },
        "list": {
          "label": "createdBy",
          "searchable": true,
          "sortable": true
        }
      },
      "updatedBy": {
        "edit": {
          "label": "updatedBy",
          "description": "",
          "placeholder": "",
          "visible": false,
          "editable": true,
          "mainField": "firstname"
        },
        "list": {
          "label": "updatedBy",
          "searchable": true,
          "sortable": true
        }
      }
    },
    "layouts": {
      "list": [
        "id",
        "widthInColumns",
        "createdAt",
        "heightInRows"
      ],
      "edit": [
        [
          {
            "name": "widthInColumns",
            "size": 4
          },
          {
            "name": "heightInRows",
            "size": 4
          }
        ],
        [
          {
            "name": "name",
            "size": 6
          },
          {
            "name": "advertisments",
            "size": 6
          }
        ]
      ]
    },
    "uid": "api::advertisement-template.advertisement-template"
  },
  "type": "object",
  "environment": null,
  "tag": null
}